{
  "Parameters": {
    "EngineConnectIncludeDir": {
      "Type": "string",
      "Description": "The path to the Engine Connect App_Confign directory"
    },
    "CommerceInstallRoot": {
      "Type": "string",
      "Description": "The root path of commerce services."
    },
    "CommerceEngineCertificateName": {
      "Type": "string",
      "Description": "The Commerce Engine certificate name for communication between Engine and Storefront."
    },
    "CommerceServicesPostfix": {
      "Type": "string",
      "Description": "The Commerce Engine postfix for services names"
    },
    "CommerceAuthoringServicesPort": {
      "Type": "string",
      "Description": "Commerce Authoring Services port"
    },
    "CommerceServicesHostPostfix": {
      "Type": "string",
      "DefaultValue": "",
      "Description": "The postfix for Commerce Engine services host names"
    }
  },
  "Variables": {
    "CommerceOps": "[concat('CommerceOps_', parameter('CommerceServicesPostfix'))]",
    "CommerceShops": "[concat('CommerceShops_', parameter('CommerceServicesPostfix'))]",
    "CommerceAuthoring": "[concat('CommerceAuthoring_', parameter('CommerceServicesPostfix'))]",
    "CommerceMinions": "[concat('CommerceMinions_', parameter('CommerceServicesPostfix'))]",
    "CommerceOpsPhysicalPath": "[joinpath(parameter('CommerceInstallRoot'),  variable('CommerceOps'))]",
    "CommerceShopsPhysicalPath": "[joinpath(parameter('CommerceInstallRoot'),  variable('CommerceShops'))]",
    "CommerceAuthoringPhysicalPath": "[joinpath(parameter('CommerceInstallRoot'),  variable('CommerceAuthoring'))]",
    "CommerceMinionsPhysicalPath": "[joinpath(parameter('CommerceInstallRoot'),  variable('CommerceMinions'))]",
    "Client.Cert.Store": "cert:\\LocalMachine\\My",
    "Security.CertificateThumbprint": "[GetCertificateThumbprint(parameter('CommerceEngineCertificateName'), variable('Client.Cert.Store'))]"
  },
  "Modules": ["InitializeCommerce"],
  "Tasks": {
    "ApplyCertificate": {
      "Type": "ApplyCertificate",
      "Params": {
        "EngineConnectIncludeDir": "[parameter('EngineConnectIncludeDir')]",
        "CertificateThumbprint": "[variable('Security.CertificateThumbprint')]",
        "CommerceServicesPathCollection": [
          "[variable('CommerceOpsPhysicalPath')]",
          "[variable('CommerceShopsPhysicalPath')]",
          "[variable('CommerceAuthoringPhysicalPath')]",
          "[variable('CommerceMinionsPhysicalPath')]"
        ]
      }
    },
    "UpdateShopsHostname": {
      "Skip": "[not(parameter('CommerceServicesHostPostfix'))]",
      "Type": "UpdateShopsHostname",
      "Params": {
        "EngineConnectIncludeDir": "[parameter('EngineConnectIncludeDir')]",
        "CommerceServicesHostPostfix": "[parameter('CommerceServicesHostPostfix')]"
      }
    },
    "UpdateShopsPort": {
      "Skip": "[parameter('CommerceServicesHostPostfix')]",
      "Type": "UpdateShopsPort",
      "Params": {
        "EngineConnectIncludeDir": "[parameter('EngineConnectIncludeDir')]",
        "CommerceAuthoringServicesPort": "[parameter('CommerceAuthoringServicesPort')]"
      }
    }
  }
}